cstack/__init__.py
cstack/_internal/templater.py
cstack/cli/app.py
cstack/cli/generators/feature.py
cstack/cli/generators/model.py
cstack/cli/generators/project.py
cstack/cli/generators/service.py
cstack/core/__init__.py
cstack/core/api.py
cstack/core/application.py
cstack/core/middleware.py
cstack/core/spa.py
cstack/templates/__init__.py.j2
cstack/templates/api_app.py.j2
cstack/templates/api_config_db.py.j2
cstack/templates/api_config_env.py.j2
cstack/templates/api_config_settings.py.j2
cstack/templates/api_model.py.j2
cstack/templates/cstack
cstack/templates/env_file.j2
cstack/templates/feature_init.py.j2
cstack/templates/feature_router.py.j2
cstack/templates/feature_test.py.j2
cstack/templates/pyproject.toml
cstack/templates/service_class.py.j2
cstack/templates/service_module.py.j2
cstack-0.1.2.dist-info/entry_points.txt
cstack-0.1.2.dist-info/LICENSE
cstack-0.1.2.dist-info/WHEEL
cstack-0.1.2.dist-info/METADATA
cstack-0.1.2.dist-info/RECORD
