Metadata-Version: 2.1
Name: cstack
Version: 0.1.2
Summary: Fullstack Python Framework. Built on Python, Vite, and Vue.
License: BSD 2-Clause
Author: Ian Kollipara
Author-email: ian.kollipara@cune.org
Requires-Python: >=3.11,<4.0
Classifier: License :: Other/Proprietary License
Classifier: Programming Language :: Python :: 3
Classifier: Programming Language :: Python :: 3.11
Requires-Dist: Jinja2 (>=3.1.2,<4.0.0)
Requires-Dist: aiofiles (>=22.1.0,<23.0.0)
Requires-Dist: fastapi (>=0.87.0,<0.88.0)
Requires-Dist: pydantic[dotenv] (>=1.10.2,<2.0.0)
Requires-Dist: rich (>=12.6.0,<13.0.0)
Requires-Dist: tortoise-orm (>=0.19.2,<0.20.0)
Requires-Dist: typer (>=0.7.0,<0.8.0)
Requires-Dist: uvicorn (>=0.20.0,<0.21.0)
